Workbook

Sheet LEEME
A1: CUMBRE 2026 · Consolidado de gastos y pagos
A2: Unifica "Cronograma_Pagos_Cumbre.xlsx" y "INVERSIÓN GIRA CUMBRE 2026.xlsx" en una sola fuente de verdad.
A4: Fecha de corte | B4: Todo el análisis está calculado al 02/09/2026 (celda B2 de la hoja TABLERO). Cambiala y se recalcula todo.
A5: Fuente 1 · CRONOGRAMA | B5: Cronograma_Pagos_Cumbre (1).xlsx — Google Drive id 1MbTsbcMKau4WA4V2-0PM7EtJv2w4XA5P. Aporta el calendario de cuotas y el histórico de pagos.
A6: Fuente 2 · MASTER | B6: INVERSIÓN GIRA CUMBRE 2026.xlsx — Google Drive id 1rRjt9YDSJKZR23nFlHJrAOf9CENc3CL2. Aporta contratos/reservas y el presupuesto línea por línea de cada evento.
A8: Cómo leer los colores | B8: Azul = dato cargado a mano (editable). Negro = fórmula. Verde = link a otra hoja de este libro. Relleno amarillo = requiere decisión tuya.
A9: Rojo / Ámbar / Verde | B9: Rojo = vencido o contradicción entre fuentes. Ámbar = vence dentro de 30 días o dato dudoso. Verde = conciliado.
A11: Supuesto de tipo de cambio | B11: Las hojas por evento del MASTER están en moneda local con tasas inconsistentes. Ver hoja EVENTOS, columna "Nota FX": ahí está la tasa que se usó para cada conversión y por qué.
A12: Supuesto de no duplicación | B12: CALENDARIO UNIFICADO (cuotas futuras y pagadas) y PAGOS REALIZADOS (histórico) son conjuntos disjuntos: el histórico termina el 03/07/2026 y el calendario empieza el 10/07/2026. Sumarlos NO duplica.
A13: Orden de las hojas de datos | B13: CALENDARIO UNIFICADO, PAGOS REALIZADOS y CONTRATOS están agrupados por país en orden de gira (Ecuador → España) y, dentro de cada país, por bloque: Lugar, Salas MM, Técnica, Producción, Dinámica, Merch, Catering, Trámites, Equipo. Cada país cierra con su subtotal.
A14: Cómo reordenar | B14: Las columnas País y Bloque están repetidas en cada fila de detalle y el filtro está activo en la fila de encabezado: podés filtrar por bloque para ver, por ejemplo, todos los pagos de Lugar de la gira. Las bandas azules son títulos, no datos: si ordenás la tabla se mezclan, mejor usá el filtro.
A16: Advertencia importante | B16: El presupuesto de la hoja EVENTOS ($1.087.979) y el calendario de pagos ($417.765) NO son comparables: el primero es el costo total de producción de cada evento, el segundo sólo los contratos con anticipo/saldo. No los sumes.
A18: Qué falta cargar | B18: Colombia 2da no tiene hoja de presupuesto en el MASTER. Perú, España y Colombia 2da no tienen ninguna cuota cargada en el calendario.
A19: Gastos de equipo en país | B19: La hoja GASTOS EQUIPO está vacía a propósito: es el destino de lo que cargue el agente de WhatsApp. Hoy esos gastos no viven en ninguno de los dos archivos originales.

Sheet TABLERO
A1: Tablero por país
A2: Presupuesto vs pagado vs pendiente. La columna "Brecha" mide cuánto se contradicen las dos fuentes. | E2: Fecha de corte → | G2: 46267
A4: País | B4: Presupuesto evento (MASTER, USD) | C4: Pagado según hoja del evento | D4: Pagado según CRONOGRAMA | E4: Brecha entre fuentes | F4: Programado (pendiente) | G4: VENCIDO al corte | H4: Fecha evento CRONOGRAMA | I4: Fecha evento MASTER | J4: Estado
A5: Ecuador | B5: 80279.73 | C5: 73773.65 | D5: 34991 | E5: =IFERROR(D5-C5,"") | H5: 25/07/2026 | I5: Quito, Ecuador Sabado 25/07/2026 Domingo 26/07/2026 | J5: fuentes no cierran
A6: Panamá | B6: 71839.07 | C6: 71372 | D6: 62012.6 | E6: =IFERROR(D6-C6,"") | H6: 08/08/2026 | I6: Panama City, Panama -Sabado 09/08/2026 Domingo 10/08/2026 | J6: fuentes no cierran
A7: Rep. Dominicana | B7: 68110.94 | C7: 68110.94 | D7: 50740 | E7: =IFERROR(D7-C7,"") | H7: 15/08/2026 | I7: Santo Domingo, Republica Dominicana -Sabado 15/08/2026 Domingo 16/08/2026 | J7: fuentes no cierran
A8: Colombia | B8: 129377.17 | D8: 86480 | E8: =IFERROR(D8-C8,"") | F8: 1522 | G8: 1522 | H8: 29/08/2026 | I8: Medellin, Colombia -Sabado 26/09/2026 Domingo 27/09/2026 | J8: VENCIDO · fuentes no cierran
A9: México | B9: 47415.59 | C9: 18916.82 | D9: 11145 | E9: =IFERROR(D9-C9,"") | F9: 26785 | G9: 26785 | H9: 05/09/2026 | I9: CDMX, Mexico -Sabado 1/11/2026 Domingo 2/11/2026 | J9: VENCIDO · fuentes no cierran
A10: Chile | B10: 148642.4 | C10: 3.48 | D10: 19693 | E10: =IFERROR(D10-C10,"") | F10: 45948 | G10: 22974 | H10: 12/09/2026 | I10: Chile -Sabado 12/09/2026 Domingo 13/09/2026 | J10: VENCIDO · fuentes no cierran
A11: Uruguay | B11: 88265.08 | D11: 1000 | E11: =IFERROR(D11-C11,"") | F11: 60612 | G11: 30306 | H11: 19/09/2026 | I11: Punta del Este, Uruguay -Sabado 19/09/2026 Domingo 20/09/2026 | J11: VENCIDO · fuentes no cierran
A12: Argentina | B12: 176159 | D12: 53494 | E12: =IFERROR(D12-C12,"") | F12: 40336 | G12: 16057 | H12: 03/10/2026 | I12: Buenos Aires, Argentina -Sabado 3/010/2026 Domingo 4/10/2026 | J12: VENCIDO · fuentes no cierran
A13: Salvador | B13: 61904.28 | D13: 7376 | E13: =IFERROR(D13-C13,"") | F13: 17213 | G13: 8606.5 | H13: 10/10/2026 | I13: San Salvador, Salvador -Sabado 07/11/2026 Domingo 08/11/2026 | J13: VENCIDO · fuentes no cierran
A14: Colombia 2da | E14: =IFERROR(D14-C14,"") | H14: 31/10/2026 | I14: sin hoja en el MASTER | J14: sin presupuesto cargado · sin pagos en el calendario
A15: Costa Rica | B15: 77920.25 | D15: 32494 | E15: =IFERROR(D15-C15,"") | F15: 32495 | H15: 07/11/2026 | I15: San José, Costa Rica -Sabado 01/08/2026 Domingo 02/08/2026 | J15: fuentes no cierran
A16: Perú | B16: 51504.27 | E16: =IFERROR(D16-C16,"") | H16: 14/11/2026 | I16: Lima, Perú -Sabado //2026 Domingo //2026 | J16: sin pagos en el calendario
A17: Guatemala | B17: 35333.97 | D17: 2000 | E17: =IFERROR(D17-C17,"") | F17: 4000 | H17: 21/11/2026 | I17: Ciudad de Guatemala, Guatemana-Sabado 14/11/2026 Domingo 15/11/2026 | J17: fuentes no cierran
A18: España | B18: 51227.61 | E18: =IFERROR(D18-C18,"") | H18: 28/11/2026 | I18: Madrid, España -Sabado 28/11/2026 Domingo 29/11/2026 | J18: sin pagos en el calendario
A19: TOTAL | B19: =SUM(B5:B18) | C19: =SUM(C5:C18) | D19: =SUM(D5:D18) | E19: =SUM(E5:E18) | F19: =SUM(F5:F18) | G19: =SUM(G5:G18)
A21: Lectura rápida
A22: Pendiente real del calendario | B22: =TABLERO!F19 | D22: Las hojas resumen del CRONOGRAMA informan $417.765,32 porque suman también las 29 cuotas ya pagadas.
A23: Vencido al corte | B23: =TABLERO!G19 | D23: 10 cuotas en estado "Programado" con fecha anterior a la fecha de corte.
A24: Brecha entre las dos fuentes | B24: =SUMPRODUCT(ABS(TABLERO!E5:E18)) | D24: Suma de diferencias absolutas: cuánto dinero está registrado como pagado en un archivo y no en el otro.

Sheet CALENDARIO UNIFICADO
A1: Calendario unificado de cuotas
A2: Las 54 cuotas del CRONOGRAMA agrupadas por país (orden de gira) y, dentro de cada país, por bloque.
A4: Bloque | B4: Fecha pago | C4: Concepto / proveedor | D4: Cuota | E4: Monto USD | F4: Estado | G4: Días vs corte | H4: Semáforo | I4: País | J4: Contradice al MASTER
A5: Ecuador · evento 25 jul
A6: LUGAR
A7: Lugar | B7: 46218 | C7: Wyndham Quintas (Salas MM) | D7: Pago total (100%) | E7: 1706 | F7: Pagado | G7: =IF(F7="Pagado","",TABLERO!$G$2-B7) | H7: =IF(F7="Pagado","PAGADO",IF(B7<TABLERO!$G$2,"VENCIDO",IF(B7<=TABLERO!$G$2+30,"< 30 dias","futuro"))) | I7: Ecuador
A8: TÉCNICA
A9: Técnica | B9: 46223 | C9: Jhon (técnica) - saldo | D9: Pago total | E9: 5500 | F9: Pagado | G9: =IF(F9="Pagado","",TABLERO!$G$2-B9) | H9: =IF(F9="Pagado","PAGADO",IF(B9<TABLERO!$G$2,"VENCIDO",IF(B9<=TABLERO!$G$2+30,"< 30 dias","futuro"))) | I9: Ecuador
A10: PRODUCCIÓN
A11: Producción | B11: 46218 | C11: Unifilas | D11: Pago total (100%) | E11: 600 | F11: Pagado | G11: =IF(F11="Pagado","",TABLERO!$G$2-B11) | H11: =IF(F11="Pagado","PAGADO",IF(B11<TABLERO!$G$2,"VENCIDO",IF(B11<=TABLERO!$G$2+30,"< 30 dias","futuro"))) | I11: Ecuador
A12: MERCH
A13: Merch | B13: 46218 | C13: Jorge (gorras, bolsas, pañuelos, camisetas) - saldo | D13: Pago total | E13: 2015 | F13: Pagado | G13: =IF(F13="Pagado","",TABLERO!$G$2-B13) | H13: =IF(F13="Pagado","PAGADO",IF(B13<TABLERO!$G$2,"VENCIDO",IF(B13<=TABLERO!$G$2+30,"< 30 dias","futuro"))) | I13: Ecuador
A14: Merch | B14: 46218 | C14: Jorge (pañuelos RD) - saldo | D14: Pago total | E14: 1075 | F14: Pagado | G14: =IF(F14="Pagado","",TABLERO!$G$2-B14) | H14: =IF(F14="Pagado","PAGADO",IF(B14<TABLERO!$G$2,"VENCIDO",IF(B14<=TABLERO!$G$2+30,"< 30 dias","futuro"))) | I14: Ecuador
A15: Merch | B15: 46218 | C15: Placas reconocimiento | D15: Pago total (100%) | E15: 390 | F15: Pagado | G15: =IF(F15="Pagado","",TABLERO!$G$2-B15) | H15: =IF(F15="Pagado","PAGADO",IF(B15<TABLERO!$G$2,"VENCIDO",IF(B15<=TABLERO!$G$2+30,"< 30 dias","futuro"))) | I15: Ecuador | J15: MASTER dice "Pendiente" (100% sin abonar)
A16: Subtotal Ecuador | E16: =SUMIF($F$6:$F$15,"<>",$E$6:$E$15) | F16: =SUMIF($F$6:$F$15,"Programado",$E$6:$E$15) | G16: pendiente →
A17: Panamá · evento 08 ago
A18: LUGAR
A19: Lugar | B19: 46219 | C19: Riu Plaza - saldo (70%) | D19: Cuota 1 de 2 (50%) | E19: 14688.66 | F19: Pagado | G19: =IF(F19="Pagado","",TABLERO!$G$2-B19) | H19: =IF(F19="Pagado","PAGADO",IF(B19<TABLERO!$G$2,"VENCIDO",IF(B19<=TABLERO!$G$2+30,"< 30 dias","futuro"))) | I19: Panamá
A20: Lugar | B20: 46219 | C20: Faranda (Salas MM) | D20: Cuota 1 de 2 (50%) | E20: 1000 | F20: Pagado | G20: =IF(F20="Pagado","",TABLERO!$G$2-B20) | H20: =IF(F20="Pagado","PAGADO",IF(B20<TABLERO!$G$2,"VENCIDO",IF(B20<=TABLERO!$G$2+30,"< 30 dias","futuro"))) | I20: Panamá | J20: La hoja Panamá registra $1.190 en Faranda + $1.375 en Hotel America Golden Tower
A21: Lugar | B21: 46232 | C21: Riu Plaza - saldo (70%) | D21: Cuota 2 de 2 (50%) | E21: 14688.66 | F21: Pagado | G21: =IF(F21="Pagado","",TABLERO!$G$2-B21) | H21: =IF(F21="Pagado","PAGADO",IF(B21<TABLERO!$G$2,"VENCIDO",IF(B21<=TABLERO!$G$2+30,"< 30 dias","futuro"))) | I21: Panamá
A22: Lugar | B22: 46232 | C22: Faranda (Salas MM) | D22: Cuota 2 de 2 (50%) | E22: 1000 | F22: Pagado | G22: =IF(F22="Pagado","",TABLERO!$G$2-B22) | H22: =IF(F22="Pagado","PAGADO",IF(B22<TABLERO!$G$2,"VENCIDO",IF(B22<=TABLERO!$G$2+30,"< 30 dias","futuro"))) | I22: Panamá | J22: La hoja Panamá registra $1.190 en Faranda + $1.375 en Hotel America Golden Tower
A23: TÉCNICA
A24: Técnica | B24: 46219 | C24: Plataforma AV | D24: Cuota 1 de 2 (50%) | E24: 7500 | F24: Pagado | G24: =IF(F24="Pagado","",TABLERO!$G$2-B24) | H24: =IF(F24="Pagado","PAGADO",IF(B24<TABLERO!$G$2,"VENCIDO",IF(B24<=TABLERO!$G$2+30,"< 30 dias","futuro"))) | I24: Panamá
A25: Técnica | B25: 46227 | C25: Plataforma AV | D25: Cuota 2 de 2 (50%) | E25: 7500 | F25: Pagado | G25: =IF(F25="Pagado","",TABLERO!$G$2-B25) | H25: =IF(F25="Pagado","PAGADO",IF(B25<TABLERO!$G$2,"VENCIDO",IF(B25<=TABLERO!$G$2+30,"< 30 dias","futuro"))) | I25: Panamá
A26: DINÁMICA
A27: Dinámica | B27: 46219 | C27: Varillas | D27: Cuota 1 de 2 (50%) | E27: 600 | F27: Pagado | G27: =IF(F27="Pagado","",TABLERO!$G$2-B27) | H27: =IF(F27="Pagado","PAGADO",IF(B27<TABLERO!$G$2,"VENCIDO",IF(B27<=TABLERO!$G$2+30,"< 30 dias","futuro"))) | I27: Panamá
A28: Dinámica | B28: 46232 | C28: Varillas | D28: Cuota 2 de 2 (50%) | E28: 600 | F28: Pagado | G28: =IF(F28="Pagado","",TABLERO!$G$2-B28) | H28: =IF(F28="Pagado","PAGADO",IF(B28<TABLERO!$G$2,"VENCIDO",IF(B28<=TABLERO!$G$2+30,"< 30 dias","futuro"))) | I28: Panamá
A29: MERCH
A30: Merch | B30: 46219 | C30: Impresos | D30: Cuota 1 de 2 (50%) | E30: 350 | F30: Pagado | G30: =IF(F30="Pagado","",TABLERO!$G$2-B30) | H30: =IF(F30="Pagado","PAGADO",IF(B30<TABLERO!$G$2,"VENCIDO",IF(B30<=TABLERO!$G$2+30,"< 30 dias","futuro"))) | I30: Panamá
A31: Merch | B31: 46222 | C31: Impresos | D31: Cuota 2 de 2 (50%) | E31: 350 | F31: Pagado | G31: =IF(F31="Pagado","",TABLERO!$G$2-B31) | H31: =IF(F31="Pagado","PAGADO",IF(B31<TABLERO!$G$2,"VENCIDO",IF(B31<=TABLERO!$G$2+30,"< 30 dias","futuro"))) | I31: Panamá
A32: Subtotal Panamá | E32: =SUMIF($F$18:$F$31,"<>",$E$18:$E$31) | F32: =SUMIF($F$18:$F$31,"Programado",$E$18:$E$31) | G32: pendiente →
A33: Rep. Dominicana · evento 15 ago
A34: LUGAR
A35: Lugar | B35: 46219 | C35: Crowne Plaza | D35: Cuota 1 de 2 (50%) | E35: 17000 | F35: Pagado | G35: =IF(F35="Pagado","",TABLERO!$G$2-B35) | H35: =IF(F35="Pagado","PAGADO",IF(B35<TABLERO!$G$2,"VENCIDO",IF(B35<=TABLERO!$G$2+30,"< 30 dias","futuro"))) | I35: Rep. Dominicana
A36: Lugar | B36: 46239 | C36: Crowne Plaza | D36: Cuota 2 de 2 (50%) | E36: 17000 | F36: Pagado | G36: =IF(F36="Pagado","",TABLERO!$G$2-B36) | H36: =IF(F36="Pagado","PAGADO",IF(B36<TABLERO!$G$2,"VENCIDO",IF(B36<=TABLERO!$G$2+30,"< 30 dias","futuro"))) | I36: Rep. Dominicana
A37: TÉCNICA
A38: Técnica | B38: 46219 | C38: Plataforma AV | D38: Cuota 1 de 2 (50%) | E38: 7500 | F38: Pagado | G38: =IF(F38="Pagado","",TABLERO!$G$2-B38) | H38: =IF(F38="Pagado","PAGADO",IF(B38<TABLERO!$G$2,"VENCIDO",IF(B38<=TABLERO!$G$2+30,"< 30 dias","futuro"))) | I38: Rep. Dominicana
A39: Técnica | B39: 46234 | C39: Plataforma AV | D39: Cuota 2 de 2 (50%) | E39: 7500 | F39: Pagado | G39: =IF(F39="Pagado","",TABLERO!$G$2-B39) | H39: =IF(F39="Pagado","PAGADO",IF(B39<TABLERO!$G$2,"VENCIDO",IF(B39<=TABLERO!$G$2+30,"< 30 dias","futuro"))) | I39: Rep. Dominicana
A40: DINÁMICA
A41: Dinámica | B41: 46219 | C41: Varillas | D41: Cuota 1 de 2 (50%) | E41: 600 | F41: Pagado | G41: =IF(F41="Pagado","",TABLERO!$G$2-B41) | H41: =IF(F41="Pagado","PAGADO",IF(B41<TABLERO!$G$2,"VENCIDO",IF(B41<=TABLERO!$G$2+30,"< 30 dias","futuro"))) | I41: Rep. Dominicana
A42: Dinámica | B42: 46239 | C42: Varillas | D42: Cuota 2 de 2 (50%) | E42: 600 | F42: Pagado | G42: =IF(F42="Pagado","",TABLERO!$G$2-B42) | H42: =IF(F42="Pagado","PAGADO",IF(B42<TABLERO!$G$2,"VENCIDO",IF(B42<=TABLERO!$G$2+30,"< 30 dias","futuro"))) | I42: Rep. Dominicana
A43: Subtotal Rep. Dominicana | E43: =SUMIF($F$34:$F$42,"<>",$E$34:$E$42) | F43: =SUMIF($F$34:$F$42,"Programado",$E$34:$E$42) | G43: pendiente →
A44: Colombia 1ra · evento 29 ago
A45: LUGAR
A46: Lugar | B46: 46223 | C46: City Hall | D46: Cuota 1 de 2 (50%) | E46: 36500 | F46: Pagado | G46: =IF(F46="Pagado","",TABLERO!$G$2-B46) | H46: =IF(F46="Pagado","PAGADO",IF(B46<TABLERO!$G$2,"VENCIDO",IF(B46<=TABLERO!$G$2+30,"< 30 dias","futuro"))) | I46: Colombia 1ra
A47: Lugar | B47: 46253 | C47: City Hall | D47: Cuota 2 de 2 (50%) | E47: 36500 | F47: Pagado | G47: =IF(F47="Pagado","",TABLERO!$G$2-B47) | H47: =IF(F47="Pagado","PAGADO",IF(B47<TABLERO!$G$2,"VENCIDO",IF(B47<=TABLERO!$G$2+30,"< 30 dias","futuro"))) | I47: Colombia 1ra
A48: MERCH
A49: Merch | B49: 46213 | C49: Gorras | D49: Cuota 1 de 1 (100%) | E49: 1000 | F49: Programado | G49: =IF(F49="Pagado","",TABLERO!$G$2-B49) | H49: =IF(F49="Pagado","PAGADO",IF(B49<TABLERO!$G$2,"VENCIDO",IF(B49<=TABLERO!$G$2+30,"< 30 dias","futuro"))) | I49: Colombia 1ra | J49: Etiqueta "Cuota 1 de 1 (100%)" pero es la 1ra mitad del saldo de $2.000
A50: Merch | B50: 46213 | C50: Camisetas | D50: Cuota 1 de 2 (50%) | E50: 216.5 | F50: Programado | G50: =IF(F50="Pagado","",TABLERO!$G$2-B50) | H50: =IF(F50="Pagado","PAGADO",IF(B50<TABLERO!$G$2,"VENCIDO",IF(B50<=TABLERO!$G$2+30,"< 30 dias","futuro"))) | I50: Colombia 1ra | J50: MASTER dice "Pendiente" (100% sin abonar, total $433)
A51: Merch | B51: 46213 | C51: 100 Tarjetas platino | D51: Cuota 1 de 2 (50%) | E51: 305.5 | F51: Programado | G51: =IF(F51="Pagado","",TABLERO!$G$2-B51) | H51: =IF(F51="Pagado","PAGADO",IF(B51<TABLERO!$G$2,"VENCIDO",IF(B51<=TABLERO!$G$2+30,"< 30 dias","futuro"))) | I51: Colombia 1ra | J51: MASTER dice "Pendiente" (100% sin abonar, total $611)
A52: Merch | B52: 46243 | C52: Gorras - saldo | D52: Cuota 2 de 2 (50%) | E52: 1000 | F52: Pagado | G52: =IF(F52="Pagado","",TABLERO!$G$2-B52) | H52: =IF(F52="Pagado","PAGADO",IF(B52<TABLERO!$G$2,"VENCIDO",IF(B52<=TABLERO!$G$2+30,"< 30 dias","futuro"))) | I52: Colombia 1ra | J52: Etiqueta "Cuota 1 de 1 (100%)" pero es la 1ra mitad del saldo de $2.000
A53: Merch | B53: 46243 | C53: Camisetas | D53: Cuota 2 de 2 (50%) | E53: 216.5 | F53: Pagado | G53: =IF(F53="Pagado","",TABLERO!$G$2-B53) | H53: =IF(F53="Pagado","PAGADO",IF(B53<TABLERO!$G$2,"VENCIDO",IF(B53<=TABLERO!$G$2+30,"< 30 dias","futuro"))) | I53: Colombia 1ra | J53: MASTER dice "Pendiente" (100% sin abonar, total $433)
A54: Merch | B54: 46243 | C54: 100 Tarjetas platino | D54: Cuota 2 de 2 (50%) | E54: 305.5 | F54: Pagado | G54: =IF(F54="Pagado","",TABLERO!$G$2-B54) | H54: =IF(F54="Pagado","PAGADO",IF(B54<TABLERO!$G$2,"VENCIDO",IF(B54<=TABLERO!$G$2+30,"< 30 dias","futuro"))) | I54: Colombia 1ra | J54: MASTER dice "Pendiente" (100% sin abonar, total $611)
A55: Merch | B55: 46249 | C55: D'vinni sas - saldo | D55: Pago total | E55: 1094 | F55: Pagado | G55: =IF(F55="Pagado","",TABLERO!$G$2-B55) | H55: =IF(F55="Pagado","PAGADO",IF(B55<TABLERO!$G$2,"VENCIDO",IF(B55<=TABLERO!$G$2+30,"< 30 dias","futuro"))) | I55: Colombia 1ra
A56: Merch | B56: 46254 | C56: Pañuelos Colombia - saldo | D56: Pago total | E56: 3475 | F56: Pagado | G56: =IF(F56="Pagado","",TABLERO!$G$2-B56) | H56: =IF(F56="Pagado","PAGADO",IF(B56<TABLERO!$G$2,"VENCIDO",IF(B56<=TABLERO!$G$2+30,"< 30 dias","futuro"))) | I56: Colombia 1ra
A57: Subtotal Colombia 1ra | E57: =SUMIF($F$45:$F$56,"<>",$E$45:$E$56) | F57: =SUMIF($F$45:$F$56,"Programado",$E$45:$E$56) | G57: pendiente →
A58: México · evento 05 sep
A59: LUGAR
A60: Lugar | B60: 46230 | C60: World Trade Center Mexiquense - saldo (50%) | D60: Cuota 1 de 2 (50%) | E60: 13392.5 | F60: Programado | G60: =IF(F60="Pagado","",TABLERO!$G$2-B60) | H60: =IF(F60="Pagado","PAGADO",IF(B60<TABLERO!$G$2,"VENCIDO",IF(B60<=TABLERO!$G$2+30,"< 30 dias","futuro"))) | I60: México
A61: Lugar | B61: 46260 | C61: World Trade Center Mexiquense - saldo (50%) | D61: Cuota 2 de 2 (50%) | E61: 13392.5 | F61: Programado | G61: =IF(F61="Pagado","",TABLERO!$G$2-B61) | H61: =IF(F61="Pagado","PAGADO",IF(B61<TABLERO!$G$2,"VENCIDO",IF(B61<=TABLERO!$G$2+30,"< 30 dias","futuro"))) | I61: México
A62: Subtotal México | E62: =SUMIF($F$59:$F$61,"<>",$E$59:$E$61) | F62: =SUMIF($F$59:$F$61,"Programado",$E$59:$E$61) | G62: pendiente →
A63: Chile · evento 12 sep
A64: LUGAR
A65: Lugar | B65: 46237 | C65: Espacio Riesco - saldo (70%) | D65: Cuota 1 de 2 (50%) | E65: 22974 | F65: Programado | G65: =IF(F65="Pagado","",TABLERO!$G$2-B65) | H65: =IF(F65="Pagado","PAGADO",IF(B65<TABLERO!$G$2,"VENCIDO",IF(B65<=TABLERO!$G$2+30,"< 30 dias","futuro"))) | I65: Chile
A66: Lugar | B66: 46267 | C66: Espacio Riesco - saldo (70%) | D66: Cuota 2 de 2 (50%) | E66: 22974 | F66: Programado | G66: =IF(F66="Pagado","",TABLERO!$G$2-B66) | H66: =IF(F66="Pagado","PAGADO",IF(B66<TABLERO!$G$2,"VENCIDO",IF(B66<=TABLERO!$G$2+30,"< 30 dias","futuro"))) | I66: Chile
A67: Subtotal Chile | E67: =SUMIF($F$64:$F$66,"<>",$E$64:$E$66) | F67: =SUMIF($F$64:$F$66,"Programado",$E$64:$E$66) | G67: pendiente →
A68: Uruguay · evento 19 sep
A69: LUGAR
A70: Lugar | B70: 46244 | C70: Centro Convenciones - saldo (70%) | D70: Cuota 1 de 2 (50%) | E70: 30306 | F70: Programado | G70: =IF(F70="Pagado","",TABLERO!$G$2-B70) | H70: =IF(F70="Pagado","PAGADO",IF(B70<TABLERO!$G$2,"VENCIDO",IF(B70<=TABLERO!$G$2+30,"< 30 dias","futuro"))) | I70: Uruguay
A71: Lugar | B71: 46274 | C71: Centro Convenciones - saldo (70%) | D71: Cuota 2 de 2 (50%) | E71: 30306 | F71: Programado | G71: =IF(F71="Pagado","",TABLERO!$G$2-B71) | H71: =IF(F71="Pagado","PAGADO",IF(B71<TABLERO!$G$2,"VENCIDO",IF(B71<=TABLERO!$G$2+30,"< 30 dias","futuro"))) | I71: Uruguay
A72: Subtotal Uruguay | E72: =SUMIF($F$69:$F$71,"<>",$E$69:$E$71) | F72: =SUMIF($F$69:$F$71,"Programado",$E$69:$E$71) | G72: pendiente →
A73: Argentina · evento 03 oct
A74: LUGAR
A75: Lugar | B75: 46258 | C75: La Rural - saldo | D75: Cuota 1 de 2 (50%) | E75: 15777 | F75: Programado | G75: =IF(F75="Pagado","",TABLERO!$G$2-B75) | H75: =IF(F75="Pagado","PAGADO",IF(B75<TABLERO!$G$2,"VENCIDO",IF(B75<=TABLERO!$G$2+30,"< 30 dias","futuro"))) | I75: Argentina
A76: Lugar | B76: 46288 | C76: La Rural - saldo | D76: Cuota 2 de 2 (50%) | E76: 15777 | F76: Programado | G76: =IF(F76="Pagado","",TABLERO!$G$2-B76) | H76: =IF(F76="Pagado","PAGADO",IF(B76<TABLERO!$G$2,"VENCIDO",IF(B76<=TABLERO!$G$2+30,"< 30 dias","futuro"))) | I76: Argentina
A77: PRODUCCIÓN
A78: Producción | B78: 46258 | C78: Intercoms | D78: Cuota 1 de 2 (50%) | E78: 280 | F78: Programado | G78: =IF(F78="Pagado","",TABLERO!$G$2-B78) | H78: =IF(F78="Pagado","PAGADO",IF(B78<TABLERO!$G$2,"VENCIDO",IF(B78<=TABLERO!$G$2+30,"< 30 dias","futuro"))) | I78: Argentina | J78: MASTER dice "Pendiente" (100%, total $560) y lo trata como pago único
A79: Producción | B79: 46288 | C79: Intercoms | D79: Cuota 2 de 2 (50%) | E79: 280 | F79: Programado | G79: =IF(F79="Pagado","",TABLERO!$G$2-B79) | H79: =IF(F79="Pagado","PAGADO",IF(B79<TABLERO!$G$2,"VENCIDO",IF(B79<=TABLERO!$G$2+30,"< 30 dias","futuro"))) | I79: Argentina | J79: MASTER dice "Pendiente" (100%, total $560) y lo trata como pago único
A80: MERCH
A81: Merch | B81: 46278 | C81: Pañuelos - saldo | D81: Pago total (100%) | E81: 5491 | F81: Programado | G81: =IF(F81="Pagado","",TABLERO!$G$2-B81) | H81: =IF(F81="Pagado","PAGADO",IF(B81<TABLERO!$G$2,"VENCIDO",IF(B81<=TABLERO!$G$2+30,"< 30 dias","futuro"))) | I81: Argentina
A82: Merch | B82: 46278 | C82: Lanyards - saldo | D82: Pago total (100%) | E82: 850 | F82: Programado | G82: =IF(F82="Pagado","",TABLERO!$G$2-B82) | H82: =IF(F82="Pagado","PAGADO",IF(B82<TABLERO!$G$2,"VENCIDO",IF(B82<=TABLERO!$G$2+30,"< 30 dias","futuro"))) | I82: Argentina
A83: Merch | B83: 46278 | C83: Gráfica ARG - saldo | D83: Pago total (100%) | E83: 1839 | F83: Programado | G83: =IF(F83="Pagado","",TABLERO!$G$2-B83) | H83: =IF(F83="Pagado","PAGADO",IF(B83<TABLERO!$G$2,"VENCIDO",IF(B83<=TABLERO!$G$2+30,"< 30 dias","futuro"))) | I83: Argentina
A84: Merch | B84: 46278 | C84: Gráfica URU - saldo | D84: Pago total (100%) | E84: 42 | F84: Programado | G84: =IF(F84="Pagado","",TABLERO!$G$2-B84) | H84: =IF(F84="Pagado","PAGADO",IF(B84<TABLERO!$G$2,"VENCIDO",IF(B84<=TABLERO!$G$2+30,"< 30 dias","futuro"))) | I84: Argentina
A85: Subtotal Argentina | E85: =SUMIF($F$74:$F$84,"<>",$E$74:$E$84) | F85: =SUMIF($F$74:$F$84,"Programado",$E$74:$E$84) | G85: pendiente →
A86: Salvador · evento 10 oct
A87: LUGAR
A88: Lugar | B88: 46265 | C88: Círculo Militar - saldo | D88: Cuota 1 de 2 (50%) | E88: 8606.5 | F88: Programado | G88: =IF(F88="Pagado","",TABLERO!$G$2-B88) | H88: =IF(F88="Pagado","PAGADO",IF(B88<TABLERO!$G$2,"VENCIDO",IF(B88<=TABLERO!$G$2+30,"< 30 dias","futuro"))) | I88: Salvador
A89: Lugar | B89: 46295 | C89: Círculo Militar - saldo | D89: Cuota 2 de 2 (50%) | E89: 8606.5 | F89: Programado | G89: =IF(F89="Pagado","",TABLERO!$G$2-B89) | H89: =IF(F89="Pagado","PAGADO",IF(B89<TABLERO!$G$2,"VENCIDO",IF(B89<=TABLERO!$G$2+30,"< 30 dias","futuro"))) | I89: Salvador
A90: Subtotal Salvador | E90: =SUMIF($F$87:$F$89,"<>",$E$87:$E$89) | F90: =SUMIF($F$87:$F$89,"Programado",$E$87:$E$89) | G90: pendiente →
A91: Costa Rica · evento 07 nov
A92: LUGAR
A93: Lugar | B93: 46293 | C93: Centro Convenciones - saldo (50%) | D93: Cuota 1 de 2 (50%) | E93: 16247.5 | F93: Programado | G93: =IF(F93="Pagado","",TABLERO!$G$2-B93) | H93: =IF(F93="Pagado","PAGADO",IF(B93<TABLERO!$G$2,"VENCIDO",IF(B93<=TABLERO!$G$2+30,"< 30 dias","futuro"))) | I93: Costa Rica
A94: Lugar | B94: 46323 | C94: Centro Convenciones - saldo (50%) | D94: Cuota 2 de 2 (50%) | E94: 16247.5 | F94: Programado | G94: =IF(F94="Pagado","",TABLERO!$G$2-B94) | H94: =IF(F94="Pagado","PAGADO",IF(B94<TABLERO!$G$2,"VENCIDO",IF(B94<=TABLERO!$G$2+30,"< 30 dias","futuro"))) | I94: Costa Rica
A95: Subtotal Costa Rica | E95: =SUMIF($F$92:$F$94,"<>",$E$92:$E$94) | F95: =SUMIF($F$92:$F$94,"Programado",$E$92:$E$94) | G95: pendiente →
A96: Guatemala · evento 21 nov
A97: LUGAR
A98: Lugar | B98: 46307 | C98: Parque de la Industria - saldo | D98: Cuota 1 de 2 (50%) | E98: 1750 | F98: Programado | G98: =IF(F98="Pagado","",TABLERO!$G$2-B98) | H98: =IF(F98="Pagado","PAGADO",IF(B98<TABLERO!$G$2,"VENCIDO",IF(B98<=TABLERO!$G$2+30,"< 30 dias","futuro"))) | I98: Guatemala
A99: Lugar | B99: 46337 | C99: Parque de la Industria - saldo | D99: Cuota 2 de 2 (50%) | E99: 1750 | F99: Programado | G99: =IF(F99="Pagado","",TABLERO!$G$2-B99) | H99: =IF(F99="Pagado","PAGADO",IF(B99<TABLERO!$G$2,"VENCIDO",IF(B99<=TABLERO!$G$2+30,"< 30 dias","futuro"))) | I99: Guatemala
A100: TRÁMITES
A101: Trámites | B101: 46307 | C101: Michelle Taylor - saldo (50%) | D101: Cuota 1 de 2 (50%) | E101: 250 | F101: Programado | G101: =IF(F101="Pagado","",TABLERO!$G$2-B101) | H101: =IF(F101="Pagado","PAGADO",IF(B101<TABLERO!$G$2,"VENCIDO",IF(B101<=TABLERO!$G$2+30,"< 30 dias","futuro"))) | I101: Guatemala
...

Sheet PAGOS REALIZADOS
A1: Histórico de pagos ejecutados (marzo–julio 2026)
A2: Anticipos previos al arranque del calendario, agrupados por país y bloque. Conjunto disjunto del CALENDARIO UNIFICADO.
A4: Bloque | B4: Fecha | C4: Proveedor / concepto | D4: % del total | E4: Monto USD | F4: País | G4: País en el archivo original
A5: Ecuador · evento 25 jul
A6: LUGAR
A7: Lugar | B7: 46106 | C7: Quorum Quito - primer pago | D7: 30% | E7: 6911 | F7: Ecuador
A8: Lugar | B8: 46205 | C8: Ambulancia - pago completo | D8: 100% | E8: 500 | F8: Ecuador
A9: TÉCNICA
A10: Técnica | B10: 46171 | C10: Técnica (Jhon) - primer pago | D10: 50% | E10: 5500 | F10: Ecuador
A11: DINÁMICA
A12: Dinámica | B12: 46204 | C12: Varillas/camerino - Cesar - pago completo | D12: 100% | E12: 4936 | F12: Ecuador
A13: MERCH
A14: Merch | B14: 46181 | C14: Mambo (impresos) - primer pago | D14: 60% | E14: 1348 | F14: Ecuador
A15: Merch | B15: 46189 | C15: Jorge (gorras, bolsas, pañuelos, camisetas) - primer pago | D15: 50% | E15: 2000 | F15: Ecuador
A16: Merch | B16: 46197 | C16: Jorge (pañuelos RD) - primer pago | D16: ? | E16: 1600 | F16: Ecuador
A17: Merch | B17: 46204 | C17: Mambo (impresos) - saldo | D17: 40% | E17: 910 | F17: Ecuador
C18: Subtotal Ecuador | E18: =SUM(E6:E17)
A19: Panamá · evento 08 ago
A20: LUGAR
A21: Lugar | B21: 46114 | C21: Riu Plaza - primer pago | D21: 30% | E21: 12590.28 | F21: Panamá
A22: MERCH
A23: Merch | B23: 46198 | C23: Camisetas y bolsas - pago completo | D23: 100% | E23: 1145 | F23: Panamá
C24: Subtotal Panamá | E24: =SUM(E20:E23)
A25: Rep. Dominicana · evento 15 ago
A26: MERCH
A27: Merch | B27: 46199 | C27: Impresos - pago completo | D27: 100% | E27: 430 | F27: Rep. Dominicana
A28: Merch | B28: 46199 | C28: Bolsas - pago completo | D28: 100% | E28: 110 | F28: Rep. Dominicana
C29: Subtotal Rep. Dominicana | E29: =SUM(E26:E28)
A30: Colombia 1ra · evento 29 ago
A31: MERCH
A32: Merch | B32: 46181 | C32: Maleta pendones - primer pago | D32: 50% | E32: 120 | F32: Colombia 1ra | G32: Colombia
A33: Merch | B33: 46181 | C33: D'vinni sas - pago completo | D33: 100% | E33: 580 | F33: Colombia 1ra | G33: Pendones
A34: Merch | B34: 46192 | C34: Gorras - primer pago | D34: 50% | E34: 2000 | F34: Colombia 1ra | G34: Colombia
A35: Merch | B35: 46196 | C35: Maleta pendones - saldo | D35: 50% | E35: 120 | F35: Colombia 1ra | G35: Colombia
A36: Merch | B36: 46198 | C36: D'vinni sas - primer pago | D36: 50% | E36: 1094 | F36: Colombia 1ra | G36: Colombia
A37: Merch | B37: 46206 | C37: Pañuelos Colombia - primer pago | D37: 50% | E37: 3475 | F37: Colombia 1ra | G37: Colombia
C38: Subtotal Colombia 1ra | E38: =SUM(E31:E37)
A39: México · evento 05 sep
A40: LUGAR
A41: Lugar | B41: 46114 | C41: World Trade Center Mexiquense - primer pago | D41: 50% | E41: 11145 | F41: México
C42: Subtotal México | E42: =SUM(E40:E41)
A43: Chile · evento 12 sep
A44: LUGAR
A45: Lugar | B45: 46198 | C45: Espacio Riesco - primer pago | D45: 30% | E45: 19693 | F45: Chile
C46: Subtotal Chile | E46: =SUM(E44:E45)
A47: Uruguay · evento 19 sep
A48: LUGAR
A49: Lugar | B49: 46114 | C49: Centro de Convenciones - primer pago | D49: 30% | E49: 1000 | F49: Uruguay
C50: Subtotal Uruguay | E50: =SUM(E48:E49)
A51: Argentina · evento 03 oct
A52: LUGAR
A53: Lugar | B53: 46139 | C53: La Rural - primer pago | D53: ? | E53: 43446 | F53: Argentina
A54: MERCH
A55: Merch | B55: 46197 | C55: Pañuelos - primer pago | D55: 50% | E55: 5491 | F55: Argentina
A56: Merch | B56: 46198 | C56: Lanyards - primer pago | D56: 50% | E56: 849 | F56: Argentina
A57: Merch | B57: 46198 | C57: Gorras - pago completo | D57: 100% | E57: 1825 | F57: Argentina
A58: Merch | B58: 46198 | C58: Gráfica ARG - primer pago | D58: 50% | E58: 642 | F58: Argentina
A59: Merch | B59: 46198 | C59: Gráfica URU - primer pago | D59: 50% | E59: 1241 | F59: Argentina
C60: Subtotal Argentina | E60: =SUM(E52:E59)
A61: Salvador · evento 10 oct
A62: LUGAR
A63: Lugar | B63: 46189 | C63: Círculo Militar - primer pago | D63: ? | E63: 7376 | F63: Salvador
C64: Subtotal Salvador | E64: =SUM(E62:E63)
A65: Costa Rica · evento 07 nov
A66: LUGAR
A67: Lugar | B67: 46163 | C67: Centro de Convenciones - primer pago | D67: 50% | E67: 32494 | F67: Costa Rica
C68: Subtotal Costa Rica | E68: =SUM(E66:E67)
A69: Guatemala · evento 21 nov
A70: LUGAR
A71: Lugar | B71: 46164 | C71: Parque de la Industria - primer pago | D71: ? | E71: 1500 | F71: Guatemala
A72: TRÁMITES
A73: Trámites | B73: 46164 | C73: Michelle Taylor - primer pago | D73: 50% | E73: 500 | F73: Guatemala
C74: Subtotal Guatemala | E74: =SUM(E70:E73)
C76: TOTAL histórico | E76: =E18+E24+E29+E38+E42+E46+E50+E60+E64+E68+E74

Sheet CONTRATOS
A1: Contratos y reservas (hoja PAGOS del MASTER)
A2: 44 contratos por país y bloque. "Saldo master" es el saldo escrito el día de la reserva: no se actualiza solo.
A4: Bloque | B4: Fecha reserva | C4: Proveedor | D4: Valor total | E4: % 1er pago | F4: 1er pago | G4: Saldo master | H4: Fecha saldo | I4: País | J4: Fila origen | K4: Alerta
A5: Ecuador · evento 25 jul
A6: LUGAR
A7: Lugar | B7: 46205 | C7: Ambulancia | D7: 500 | E7: 1 | I7: Ecuador | J7: 32 | K7: Contrato sin ningún dato de pago en el MASTER
A8: Lugar | B8: 46106 | C8: Quorum Quito | D8: 25456 | E8: 0.3 | F8: 6911 | G8: 18545 | I8: Ecuador | J8: 7
A9: SALAS MM
A10: Salas MM | C10: Wyndham Quintas | D10: 1706 | I10: Ecuador | J10: 45 | K10: Contrato sin ningún dato de pago en el MASTER
A11: TÉCNICA
A12: Técnica | B12: 46171 | C12: Tecnica (Jhon) | D12: 11000 | E12: 0.5 | F12: 5500 | G12: 5500 | H12: 46223 | I12: Ecuador | J12: 14
A13: PRODUCCIÓN
A14: Producción | C14: Unifilas | D14: 600 | I14: Ecuador | J14: 42 | K14: Contrato sin ningún dato de pago en el MASTER
A15: DINÁMICA
A16: Dinámica | B16: 46204 | C16: Varillas/camerino - Cesar | D16: 4936 | E16: 1 | I16: Ecuador | J16: 31 | K16: Contrato sin ningún dato de pago en el MASTER
A17: MERCH
A18: Merch | B18: 46189 | C18: Jorge (Gorras, bolsas, pañuelos, camisetas) | D18: 4015 | E18: 0.5 | F18: 2000 | G18: 2015 | H18: 46218 | I18: Ecuador | J18: 18
A19: Merch | B19: 46197 | C19: Jorge (pañuelos RD) | D19: 2675 | E19: ? | F19: 1600 | G19: 1075 | H19: 46218 | I19: Ecuador | J19: 20 | K19: % del primer pago desconocido
A20: Merch | B20: 46181 | C20: Mambo (impresos) | D20: 2246 | E20: 0.6 | F20: 1347.6 | G20: 898.4 | H20: 46204 | I20: Ecuador | J20: 15
A21: Merch | C21: Placas reconocimiento | D21: 390 | E21: 1 | F21: Pendiente | I21: Ecuador | J21: 35 | K21: Sin abonar según MASTER — revisar contra el CALENDARIO
A22: CATERING
A23: Catering | B23: 46205 | C23: Quorum Quito | D23: 5074 | E23: 1 | F23: Pendiente | I23: Ecuador | J23: 33 | K23: Sin abonar según MASTER — revisar contra el CALENDARIO
C24: Subtotal Ecuador | D24: =SUM(D6:D23) | G24: =SUM(G6:G23)
A25: Panamá · evento 08 ago
A26: LUGAR
A27: Lugar | B27: 46114 | C27: Riu plaza | D27: 41967.6 | E27: 0.3 | F27: 12590.28 | G27: 29377.32 | I27: Panamá | J27: 6
A28: SALAS MM
A29: Salas MM | C29: Faranda | D29: 2000 | I29: Panamá | J29: 44 | K29: Contrato sin ningún dato de pago en el MASTER
A30: TÉCNICA
A31: Técnica | C31: Plataforma AV | D31: 15000 | I31: Panamá | J31: 46 | K31: Contrato sin ningún dato de pago en el MASTER
A32: DINÁMICA
A33: Dinámica | C33: VArillas | D33: 1200 | E33: aprox | I33: Panamá | J33: 49 | K33: Contrato sin ningún dato de pago en el MASTER
A34: MERCH
A35: Merch | B35: 46198 | C35: Camisetas y bolsas | D35: 1145 | E35: 1 | F35: 1145 | I35: Panamá | J35: 28
A36: Merch | C36: Impresos | D36: 700 | I36: Panamá | J36: 48 | K36: Contrato sin ningún dato de pago en el MASTER
C37: Subtotal Panamá | D37: =SUM(D26:D36) | G37: =SUM(G26:G36)
A38: Rep. Dominicana · evento 15 ago
A39: LUGAR
A40: Lugar | C40: Crowne plaza | D40: 34000 | I40: Rep. Dominicana | J40: 43 | K40: Contrato sin ningún dato de pago en el MASTER
A41: TÉCNICA
A42: Técnica | C42: Plataforma AV | D42: 15000 | I42: Rep. Dominicana | J42: 47 | K42: Contrato sin ningún dato de pago en el MASTER
A43: DINÁMICA
A44: Dinámica | C44: Varillas | D44: 1200 | E44: aprox | I44: Rep. Dominicana | J44: 50 | K44: Contrato sin ningún dato de pago en el MASTER
A45: MERCH
A46: Merch | B46: 46199 | C46: Bolsas | D46: 110 | E46: 1 | I46: Rep. Dominicana | J46: 30 | K46: Contrato sin ningún dato de pago en el MASTER
A47: Merch | B47: 46199 | C47: Impresos | D47: 430 | E47: 1 | I47: Rep. Dominicana | J47: 29 | K47: Contrato sin ningún dato de pago en el MASTER
C48: Subtotal Rep. Dominicana | D48: =SUM(D39:D47) | G48: =SUM(G39:G47)
A49: Colombia 1ra · evento 29 ago
A50: LUGAR
A51: Lugar | C51: City Hall | D51: 73000 | I51: Colombia 1ra | J51: 41 | K51: Contrato sin ningún dato de pago en el MASTER
A52: MERCH
A53: Merch | C53: 100 Tarjetas platino | D53: 611 | E53: 1 | F53: Pendiente | I53: Colombia 1ra | J53: 37 | K53: Sin abonar según MASTER — revisar contra el CALENDARIO
A54: Merch | C54: Camisetas | D54: 433 | E54: 1 | F54: Pendiente | I54: Colombia 1ra | J54: 36 | K54: Sin abonar según MASTER — revisar contra el CALENDARIO
A55: Merch | B55: 46181 | C55: D´vinni sas | D55: 580 | E55: 1 | F55: 580 | G55: 0 | I55: Colombia 1ra | J55: 17
A56: Merch | B56: 46198 | C56: D´vinni sas | D56: 2188 | E56: 0.5 | F56: 1094 | G56: 1094 | H56: 46249 | I56: Colombia 1ra | J56: 27
A57: Merch | B57: 46192 | C57: Gorras | D57: 4000 | E57: 0.5 | F57: 2000 | G57: 2000 | I57: Colombia 1ra | J57: 19
A58: Merch | B58: 46181 | C58: Maleta para pendones | D58: 240 | E58: 0.5 | F58: 120 | G58: 120 | H58: 46196 | I58: Colombia 1ra | J58: 16
A59: Merch | B59: 46206 | C59: Pañuelos Colombia | D59: 6950 | E59: 0.5 | F59: 3475 | H59: 46254 | I59: Colombia 1ra | J59: 34
C60: Subtotal Colombia 1ra | D60: =SUM(D50:D59) | G60: =SUM(G50:G59)
A61: México · evento 05 sep
A62: LUGAR
A63: Lugar | B63: 46114 | C63: World trade center Mexiquense | D63: 37930 | E63: ? | F63: 11145 | G63: 26785 | I63: México | J63: 5 | K63: % del primer pago desconocido
C64: Subtotal México | D64: =SUM(D62:D63) | G64: =SUM(G62:G63)
A65: Chile · evento 12 sep
A66: MERCH
A67: Merch | B67: 46198 | C67: Espacio Riesco | D67: 65641 | E67: 0.3 | F67: 19692.72 | G67: 45948.28 | I67: Chile | J67: 26
C68: Subtotal Chile | D68: =SUM(D66:D67) | G68: =SUM(G66:G67)
A69: Uruguay · evento 19 sep
A70: LUGAR
A71: Lugar | B71: 46114 | C71: Centro de Convenciones | D71: 61612 | E71: 0.3 | F71: 1000 | G71: 60612 | I71: Uruguay | J71: 8
C72: Subtotal Uruguay | D72: =SUM(D70:D71) | G72: =SUM(G70:G71)
A73: Argentina · evento 03 oct
A74: LUGAR
A75: Lugar | B75: 46139 | C75: La Rural | D75: 75000 | E75: ? | F75: 43446 | G75: 31554 | I75: Argentina | J75: 11 | K75: % del primer pago desconocido
A76: PRODUCCIÓN
A77: Producción | C77: Intercoms | D77: 560 | E77: 1 | F77: Pendiente | I77: Argentina | J77: 38 | K77: Sin abonar según MASTER — revisar contra el CALENDARIO
A78: MERCH
A79: Merch | B79: 46198 | C79: GORRAS | D79: 1825 | E79: 0.5 | F79: 1825 | G79: 0 | I79: Argentina | J79: 23
A80: Merch | B80: 46198 | C80: GRAFICA ARG | D80: 2481 | E80: 0.5 | F80: 642 | G80: 1839 | I80: Argentina | J80: 24
A81: Merch | B81: 46198 | C81: GRAFICA URU | D81: 1283 | E81: 0.5 | F81: 1241 | G81: 42 | I81: Argentina | J81: 25
A82: Merch | B82: 46198 | C82: LANYARDS | D82: 1698.59 | E82: 0.5 | F82: 849 | G82: 849.59 | I82: Argentina | J82: 22
A83: Merch | B83: 46197 | C83: Pañuelos | D83: 10982 | E83: 0.5 | F83: 5491 | G83: 5491 | I83: Argentina | J83: 21
C84: Subtotal Argentina | D84: =SUM(D74:D83) | G84: =SUM(G74:G83)
A85: Salvador · evento 10 oct
A86: LUGAR
A87: Lugar | B87: 46189 | C87: Circulo militar | D87: 24589 | E87: ? | F87: 7376 | G87: 17213 | I87: Salvador | J87: 9 | K87: % del primer pago desconocido
C88: Subtotal Salvador | D88: =SUM(D86:D87) | G88: =SUM(G86:G87)
A89: Costa Rica · evento 07 nov
A90: LUGAR
A91: Lugar | B91: 46163 | C91: Centro de Convenciones | D91: 64989 | E91: 0.5 | F91: 32494 | G91: 32495 | I91: Costa Rica | J91: 10
C92: Subtotal Costa Rica | D92: =SUM(D90:D91) | G92: =SUM(G90:G91)
A93: Guatemala · evento 21 nov
A94: LUGAR
A95: Lugar | B95: 46164 | C95: Parque de la industria | D95: 5000 | E95: ? | F95: 1500 | G95: 3500 | I95: Guatemala | J95: 13 | K95: % del primer pago desconocido
A96: TRÁMITES
A97: Trámites | B97: 46164 | C97: Michelle Taylor | D97: 1000 | E97: 0.5 | F97: 500 | G97: 500 | I97: Guatemala | J97: 12
C98: Subtotal Guatemala | D98: =SUM(D94:D97) | G98: =SUM(G94:G97)
C100: TOTAL contratado | D100: =D24+D37+D48+D60+D64+D68+D72+D84+D88+D92+D98 | G100: =G24+G37+G48+G60+G64+G68+G72+G84+G88+G92+G98

Sheet EVENTOS
A1: Presupuesto por evento y tipos de cambio
A2: Cada hoja del MASTER está en su moneda. Acá se documenta la tasa usada y por qué.
A4: País | B4: Hoja origen | C4: Moneda | D4: Total en moneda local | E4: Tasa a USD | F4: Total USD | G4: Pagado local | H4: Pagado USD | I4: Nota FX | J4: Fecha en el MASTER
A5: Ecuador | B5: Ecuador (25 Jul-26 Jul) | C5: USD | D5: 80279.725 | E5: 1 | F5: =D5*E5 | G5: 73773.65 | H5: =IF(G5="","",G5*E5) | I5: USD directo | J5: Quito, Ecuador Sabado 25/07/2026 Domingo 26/07/2026
A6: Panamá | B6: Panama (09 ago-10 ago) | C6: USD | D6: 71839.065 | E6: 1 | F6: =D6*E6 | G6: 71372 | H6: =IF(G6="","",G6*E6) | I6: USD directo | J6: Panama City, Panama -Sabado 09/08/2026 Domingo 10/08/2026
A7: Rep. Dominicana | B7: Rep D. (15 ago-16 ago) | C7: USD | D7: 68110.941 | E7: 1 | F7: =D7*E7 | G7: 68110.941 | H7: =IF(G7="","",G7*E7) | I7: Hoja ya en USD (tasa 1.0) | J7: Santo Domingo, Republica Dominicana -Sabado 15/08/2026 Domingo 16/08/2026
A8: Colombia | B8: Colombia (29 ago - 30 ago) | C8: COP | D8: 478695540 | E8: 0.00027027027 | F8: =D8*E8 | G8: 0 | H8: =IF(G8="","",G8*E8) | I8: Presupuesto /3700; la columna PAGADO usa /4080 | J8: Medellin, Colombia -Sabado 26/09/2026 Domingo 27/09/2026
A9: México | B9: Mexico (5 sep - 6 sep) | C9: MXN | D9: 803654 | E9: 0.059 | F9: =D9*E9 | G9: 320624 | H9: =IF(G9="","",G9*E9) | I9: Presupuesto x0.059; la columna PAGADO usa x0.051 | J9: CDMX, Mexico -Sabado 1/11/2026 Domingo 2/11/2026
A10: Chile | B10: Chile (12 sep-13 sep) | C10: USD | D10: 148642.4 | E10: 1 | F10: =D10*E10 | G10: 3.485 | H10: =IF(G10="","",G10*E10) | I10: Celda de tasa vacia/0 -> se toma como USD | J10: Chile -Sabado 12/09/2026 Domingo 13/09/2026
A11: Uruguay | B11: Uruguay (19 sep-20 sep) | C11: USD | D11: 88265.08 | E11: 1 | F11: =D11*E11 | G11: 0 | H11: =IF(G11="","",G11*E11) | I11: Celda de tasa 0 -> se toma como USD | J11: Punta del Este, Uruguay -Sabado 19/09/2026 Domingo 20/09/2026
A12: Costa Rica | B12: Costa Rica (1 ago-2 ago) | C12: USD | D12: 77920.246 | E12: 1 | F12: =D12*E12 | G12: 0 | H12: =IF(G12="","",G12*E12) | I12: Sin celda de tasa | J12: San José, Costa Rica -Sabado 01/08/2026 Domingo 02/08/2026
A13: Argentina | B13: Argentina (3 oct-4 oct) | C13: USD | D13: 176159 | E13: 1 | F13: =D13*E13 | G13: 0 | H13: =IF(G13="","",G13*E13) | I13: Tasa 1.0 | J13: Buenos Aires, Argentina -Sabado 3/010/2026 Domingo 4/10/2026
A14: Salvador | B14: Salvador (7 nov-8 nov) | C14: USD | D14: 61904.281 | E14: 1 | F14: =D14*E14 | G14: 0 | H14: =IF(G14="","",G14*E14) | I14: Tasa heredada de Mexico (link roto) | J14: San Salvador, Salvador -Sabado 07/11/2026 Domingo 08/11/2026
A15: Guatemala | B15: Guatemala (14 nov-15 nov) | C15: USD | D15: 35333.97 | E15: 1 | F15: =D15*E15 | G15: 0 | H15: =IF(G15="","",G15*E15) | I15: Tasa heredada de Mexico (link roto) | J15: Ciudad de Guatemala, Guatemana-Sabado 14/11/2026 Domingo 15/11/2026
A16: Perú | B16: Perú | C16: USD | D16: 51504.27 | E16: 1 | F16: =D16*E16 | G16: 0 | H16: =IF(G16="","",G16*E16) | I16: Tasa heredada de Mexico (link roto) | J16: Lima, Perú -Sabado //2026 Domingo //2026
A17: España | B17: España (28 nov-29 nov) | C17: EUR | D17: 44545.75 | E17: 1.15 | F17: =D17*E17 | G17: 0 | H17: =IF(G17="","",G17*E17) | I17: EUR x1.15 | J17: Madrid, España -Sabado 28/11/2026 Domingo 29/11/2026
A18: TOTAL | F18: =SUM(F5:F17) | H18: =SUM(H5:H17)
A20: Colombia 2da (31/10/2026) no tiene hoja de presupuesto en el MASTER: su costo no está dentro de este total.

Sheet HALLAZGOS
A1: Hallazgos de la conciliación
A2: Ordenados por impacto. La columna "Acción" es lo que hay que decidir.
A4: # | B4: Severidad | C4: Hallazgo | D4: Evidencia | E4: Impacto USD | F4: Acción
A5: 1 | B5: ALTA | C5: El informe quincenal sobrestima el pendiente | D5: Las hojas PRESUPUESTO QUINCENAL y VISTA POR EVENTO suman las 54 filas del calendario, incluidas las 29 ya marcadas "Pagado". Informan $417.765,32 de pendiente. | E5: 188854.32 | F5: Reemplazar el informe a finanzas por la hoja TABLERO. Pendiente real: $228.911,00.
A6: 2 | B6: ALTA | C6: Cuotas vencidas sin pagar | D6: 10 cuotas en estado "Programado" con fecha anterior al 02/09/2026. La más vieja lleva 54 días (Colombia merch, 10/07). | E6: 106250.5 | F6: Confirmar con Erick cuáles se pagaron y no se marcaron, y cuáles están realmente en mora.
A7: 3 | B7: ALTA | C7: Las dos fuentes no cierran en pagos | D7: Suma de diferencias absolutas por país entre "pagado según la hoja del evento" y "pagado según el cronograma". | E7: 275818.32 | F7: Definir cuál archivo es la fuente de verdad de PAGOS. Propuesta: el consolidado, alimentado por el agente.
A8: 4 | B8: ALTA | C8: Colombia: $86.480 pagados que la hoja del evento reporta como $0 | D8: City Hall 2 x $36.500 + merch figuran "Pagado" en el cronograma. Las 64 líneas de la hoja Colombia tienen la columna Pago en 0. | E8: 86480 | F8: Cargar los pagos en la hoja de Colombia o migrar a este consolidado.
A9: 5 | B9: ALTA | C9: Fechas de evento en conflicto entre archivos | D9: Colombia: 29/08 vs 26-27/09 · México: 05/09 vs 01-02/11 · Costa Rica: 07/11 vs 01-02/08 · Salvador: 10/10 vs 07-08/11 · Guatemala: 21/11 vs 14-15/11 · Panamá: 08/08 vs 09-10/08. | F9: Fijar el calendario real de la gira. Toda la regla de pagos ("Lugar: 10 días antes") depende de esta fecha.
A10: 6 | B10: ALTA | C10: 14 contratos sin ningún dato de pago en el MASTER | D10: City Hall $73.000, Crowne Plaza $34.000, Plataforma AV Panamá y RD $15.000 c/u, Faranda $2.000, Wyndham Quintas $1.706, Varillas, Impresos, Unifilas, Ambulancia, Bolsas. | E10: 150382 | F10: La única traza de esos pagos es el cronograma. Adjuntar comprobantes antes del cierre contable.
A11: 7 | B11: MEDIA | C11: Salvador tiene dos sedes vivas | D11: Contrato pagado y programado: Círculo Militar ($24.589, $7.376 abonado). La hoja del evento presupuesta Hotel Hilton ($31.000 sala + $7.890 técnica). | E11: 31000 | F11: Confirmar sede con Aleja. Si se cambió, reclamar o reasignar el anticipo del Círculo Militar.
A12: 8 | B12: MEDIA | C12: Panamá: sala Mastermind pagada en dos hoteles | D12: El cronograma pagó Faranda "Salas MM" $2.000 en dos cuotas. La hoja Panamá registra $1.190 en Faranda y $1.375 en Hotel America Golden Tower, ambos pagados. | E12: 810 | F12: Reclamar el crédito no usado en Faranda (~$810).
A13: 9 | B13: MEDIA | C13: Contradicciones de estado en 5 conceptos | D13: Placas reconocimiento EC $390, Camisetas CO $433, Tarjetas platino CO $611, Intercoms AR $560: el cronograma los da por pagados o parcialmente pagados, el MASTER dice "Pendiente". | E13: 1994 | F13: Verificar contra extractos bancarios y unificar el estado en este consolidado.
A14: 10 | B14: MEDIA | C14: Ecuador cerró con saldo sin liquidar | D14: Evento del 25-26/07. Quinta by Wyndham: hospedaje $3.110 y salas MM/empresarios $2.082 sin pagar. Vuelos LATAM cruzados: $1.564 imputados a un sobrepeso de $260 y sólo $299 de $2.917 de vuelos. | E14: 6506.07 | F14: Liquidar con el hotel y corregir la imputación de LATAM.
A15: 11 | B15: MEDIA | C15: Ecuador: catering $5.074 nunca programado | D15: El MASTER lo marca "Pendiente"; el cronograma no tiene ninguna fila para el catering de Quorum Quito. El evento ya ocurrió. | E15: 5074 | F15: Confirmar si se pagó. Si no, es una deuda vencida hace 5 semanas.
A16: 12 | B16: MEDIA | C16: Guatemala: presupuesto 3x el contrato | D16: Contrato Parque de la Industria $5.000 ($1.500 abonado, saldo $3.500 en 2 cuotas). La hoja del evento presupuesta $14.351 de ítems del mismo venue. | E16: 9351 | F16: Pedir cotización firme a Michelle Taylor antes de fijar las cuotas de octubre y noviembre.
A17: 13 | B17: MEDIA | C17: Tres eventos sin ninguna cuota cargada | D17: Colombia 2da (31/10), Perú (14/11) y España (28/11) figuran con "-" en el cronograma. Perú y España tienen $51.504 y $51.228 de presupuesto; Colombia 2da no tiene ni hoja. | E17: 102732 | F17: Cargar contratos y fechas de pago. Son los tres últimos eventos del año y hoy no tienen plan financiero.
A18: 14 | B18: MEDIA | C18: Tipos de cambio incoherentes dentro de la misma hoja | D18: México usa 0,059 para presupuestar y 0,051 para pagos. Colombia usa 3.700 y 4.080. Chile y Uruguay tienen la celda de tasa en 0. Salvador, Guatemala y Perú apuntan al link de "peso mexicano a dólar" heredado por copiar la hoja. | F18: Fijar una tasa por evento en la hoja EVENTOS y usarla en todas las columnas.
A19: 15 | B19: BAJA | C19: El "Gral Resume" del MASTER está roto | D19: La columna PAGADO da #REF! en Guatemala y Perú, $0 en Panamá, Colombia, Argentina, Uruguay y España, y $3,48 en Chile. | F19: Dejar de usarlo. La hoja TABLERO lo reemplaza.
A20: 16 | B20: BAJA | C20: Etiquetas de cuota inconsistentes | D20: Colombia Gorras: una fila dice "Cuota 1 de 1 (100%)" por $1.000 y otra "Cuota 2 de 2 (50%)" por $1.000, cuando son las dos mitades del mismo saldo de $2.000. | F20: Normalizar el texto de cuota. El agente lo va a generar automáticamente.

Sheet GASTOS EQUIPO
A1: Gastos del equipo en país
A2: Hoja destino del agente de WhatsApp. Hoy estos gastos no existen en ninguno de los dos archivos originales.
A3: Fila 5 = ejemplo con formato esperado (tomado de la factura 2601020 de Panamá). Borrala cuando el agente empiece a escribir.
A4: ID | B4: Fecha | C4: País / evento | D4: Persona | E4: Rol | F4: Comercio / proveedor | G4: Concepto | H4: Categoría | I4: Moneda | J4: Monto local | K4: Tasa | L4: Monto USD | M4: Comprobante | N4: Estado | O4: N° factura reintegro
A5: GE-2026-0001 | B5: 46243 | C5: Panamá | D5: Carlos Andrés Calderón Arbeláez | E5: Staff | F5: Riba Smith | G5: Camerinos speakers / staff | H5: Camerinos | I5: USD | J5: 133.81 | K5: 1 | L5: =J5*K5 | M5: foto ticket WhatsApp | N5: Facturado | O5: 2601020
L6: =IF(J6="","",J6*K6)
L7: =IF(J7="","",J7*K7)
L8: =IF(J8="","",J8*K8)
L9: =IF(J9="","",J9*K9)
L10: =IF(J10="","",J10*K10)
L11: =IF(J11="","",J11*K11)
L12: =IF(J12="","",J12*K12)
L13: =IF(J13="","",J13*K13)
L14: =IF(J14="","",J14*K14)
L15: =IF(J15="","",J15*K15)
L16: =IF(J16="","",J16*K16)
L17: =IF(J17="","",J17*K17)
... L59: =IF(J59="","",J59*K59)
